<Defs>
	<!-- SeedsPlease :: RG_Plant_RaspberryCultivated(regrowth.botr.core)Autogenerated as Seed_RG_RaspberryCultivated-->
	<ThingDef ParentName="SeedBase">
		<defName>Seed_RG_RaspberryCultivated</defName>
		<label>cultivated raspberry seeds</label>
		<descriptionHyperlinks>
			<ThingDef>RG_Plant_RaspberryCultivated</ThingDef>
		</descriptionHyperlinks>
		<modExtensions>
			<li Class="SeedsPleaseLite.Seed">
				<sources>
					<li>RG_Plant_RaspberryCultivated</li>
				</sources>
			</li>
		</modExtensions>
	</ThingDef>
	
	<!-- SeedsPlease :: RG_Plant_BerryCultivated(regrowth.botr.core)Autogenerated as Seed_RG_BerryCultivated-->
	<ThingDef ParentName="SeedBase">
		<defName>Seed_RG_BerryCultivated</defName>
		<label>cultivated berry seeds</label>
		<descriptionHyperlinks>
			<ThingDef>RG_Plant_BerryCultivated</ThingDef>
		</descriptionHyperlinks>
		<modExtensions>
			<li Class="SeedsPleaseLite.Seed">
				<sources>
					<li>RG_Plant_BerryCultivated</li>
				</sources>
			</li>
		</modExtensions>
	</ThingDef>
</Defs>
